{
    "admin": {
        "listen": "167.235.155.72:2019"
    },
    "apps": {
        "http": {
            "servers": {
                "Cloud_Guardian": {
                    "listen": [
                        ":80"
                    ],
                    "timeouts": {
                        "read_header_timeout": "15s",
                        "idle_timeout": "5m",
                        "write_timeout": "15s",
                        "header_timeout": "10s"
                    },
                    "max_connections": 50,
                    "max_requests_per_connection": 20,
                    "routes": [
                        {
                            "match": [
                                {
                                    "path": [
                                        "/login"
                                    ]
                                }
                            ],
                            "handle": [
                                {
                                    "handler": "rate_limit",
                                    "rate_limit": {
                                        "requests": 3,
                                        "window": "1m"
                                    }
                                },
                                {
                                    "handler": "authenticate",
                                    "basic": {
                                        "users": {
                                            "Alberto": "5678"
                                        }
                                    }
                                },
                                {
                                    "handler": "static_response",
                                    "body": "Acceso a /login concedido"
                                }
                            ]
                        },
                        {
                            "match": [
                                {
                                    "path": [
                                        "/api/*"
                                    ]
                                }
                            ],
                            "handle": [
                                {
                                    "handler": "reverse_proxy",
                                    "upstreams": [
                                        {
                                            "dial": "localhost:5000"
                                        }
                                    ]
                                }
                            ]
                        },
                        {
                            "match": [
                                {
                                    "path": [
                                        "/"
                                    ]
                                }
                            ],
                            "handle": [
                                {
                                    "handler": "static_response",
                                    "body": "P\u00e1gina principal accesible para IPs permitidas"
                                }
                            ]
                        }
                    ]
                }
            },
            "security": {
                "remote_ip": {
                    "allow": [
                        "100.10.10.1",
                        "192.168.1.100"
                    ],
                    "deny": [
                        "0.0.0.0/0",
                        "192.168.0.0/24"
                    ]
                }
            }
        }
    }
}